c_test9_cc/__init__.py
c_test9_cc/core.py
c_test9_cc/log.py
c_test9_cc/server.py
c_test9_cc-0.1.2.dist-info/METADATA
c_test9_cc-0.1.2.dist-info/WHEEL
c_test9_cc-0.1.2.dist-info/top_level.txt
c_test9_cc-0.1.2.dist-info/RECORD
