Metadata-Version: 2.4
Name: c-test9-cc
Version: 0.1.2
Summary: Add your description here
Requires-Python: >=3.13
Requires-Dist: anyio>=4.10.0
Requires-Dist: fastapi>=0.116.2
Requires-Dist: pytest>=8.4.2
Requires-Dist: pytest-asyncio>=1.2.0
Requires-Dist: pytest-tornasync>=0.6.0.post2
Requires-Dist: toml>=0.10.2
Requires-Dist: uvicorn>=0.36.0
